{
  "legislative_session": "119",
  "identifier": "HR 4553",
  "title": "Energy and Water Development and Related Agencies Appropriations Act, 2026",
  "from_organization": "~{\"classification\": \"lower\"}",
  "classification": [
    "bill"
  ],
  "subject": [],
  "abstracts": [],
  "other_titles": [
    {
      "note": "",
      "title": "Making appropriations for energy and water development and related agencies for the fiscal year ending September 30, 2026, and for other purposes."
    }
  ],
  "other_identifiers": [],
  "actions": [
    {
      "description": "Committee of the Whole House on the state of the Union rises leaving H.R. 4553 as unfinished business.",
      "date": "2025-09-04T02:11:19+00:00",
      "organization_id": "~{\"classification\": \"lower\"}",
      "classification": [],
      "related_entities": []
    },
    {
      "description": "On motion that the committee rise Agreed to by voice vote.",
      "date": "2025-09-04T02:11:09+00:00",
      "organization_id": "~{\"classification\": \"lower\"}",
      "classification": [],
      "related_entities": []
    },
    {
      "description": "Mr. Fleischmann moved that the committee rise.",
      "date": "2025-09-04T02:10:49+00:00",
      "organization_id": "~{\"classification\": \"lower\"}",
      "classification": [],
      "related_entities": []
    },
    {
      "description": "The House resolved into Committee of the Whole House on the state of the Union for further consideration.",
      "date": "2025-09-04T01:40:59+00:00",
      "organization_id": "~{\"classification\": \"lower\"}",
      "classification": [],
      "related_entities": []
    },
    {
      "description": "Considered as unfinished business. (consideration: CR H3821-3826: 1)",
      "date": "2025-09-04T01:40:46+00:00",
      "organization_id": "~{\"classification\": \"lower\"}",
      "classification": [],
      "related_entities": []
    },
    {
      "description": "POSTPONED PROCEEDINGS - At the conclusion of debate on the Perry amendment No. 30, the Chair put the question on agreeing to the amendment and by voice vote, announced the ayes had prevailed. Ms. Kaptur demanded a recorded vote, and the Chair postponed further proceedings until a time to be announced.",
      "date": "2025-09-03T22:09:31+00:00",
      "organization_id": "~{\"classification\": \"lower\"}",
      "classification": [],
      "related_entities": []
    },
    {
      "description": "DEBATE - Pursuant to the provisions of H. Res. 672, the Committee of the Whole proceeded with 10 minutes of debate on the Perry amendment No. 30.",
      "date": "2025-09-03T22:04:41+00:00",
      "organization_id": "~{\"classification\": \"lower\"}",
      "classification": [],
      "related_entities": []
    },
    {
      "description": "POSTPONED PROCEEDINGS - At the conclusion of debate on the Perry amendment No. 29, the Chair put the question on agreeing to the amendment and by voice vote, announced the ayes had prevailed. Ms. Kaptur demanded a recorded vote, and the Chair postponed further proceedings until a time to be announced.",
      "date": "2025-09-03T22:03:56+00:00",
      "organization_id": "~{\"classification\": \"lower\"}",
      "classification": [],
      "related_entities": []
    },
    {
      "description": "DEBATE - Pursuant to the provisions of H. Res. 672, the Committee of the Whole proceeded with 10 minutes of debate on the Perry amendment No. 29.",
      "date": "2025-09-03T21:59:34+00:00",
      "organization_id": "~{\"classification\": \"lower\"}",
      "classification": [],
      "related_entities": []
    },
    {
      "description": "POSTPONED PROCEDDINGS - At the conclusion of debate on the Perry amendment No. 28, the Chair put the question on agreeing to the amendment and by voice vote, announced the ayes had prevailed. Ms. Kaptur demanded a recorded vote, and the Chair postponed further proceedings until a time to be announced.",
      "date": "2025-09-03T21:58:36+00:00",
      "organization_id": "~{\"classification\": \"lower\"}",
      "classification": [],
      "related_entities": []
    },
    {
      "description": "DEBATE - Pursuant to the provisions of H. Res. 672, the Committee of the Whole proceeded with 10 minutes of debate on the Perry amendment No. 28.",
      "date": "2025-09-03T21:51:55+00:00",
      "organization_id": "~{\"classification\": \"lower\"}",
      "classification": [],
      "related_entities": []
    },
    {
      "description": "POSTPONED PROCEEDINGS - At the conclusion of debate on the Perry amendment No. 27, the Chair put the question on agreeing to the amendment and by voice vote, announced the ayes had prevailed. Mr. Fleischmann demanded a recorded vote, and the Chair postponed further proceedings until a time to be announced.",
      "date": "2025-09-03T21:51:03+00:00",
      "organization_id": "~{\"classification\": \"lower\"}",
      "classification": [],
      "related_entities": []
    },
    {
      "description": "DEBATE - Pursuant to the provisions of H. Res. 672, the Committee of the Whole proceeded with 10 minutes of debate on the Perry amendment No. 27.",
      "date": "2025-09-03T21:45:12+00:00",
      "organization_id": "~{\"classification\": \"lower\"}",
      "classification": [],
      "related_entities": []
    },
    {
      "description": "POSTPONED PROCEEDINGS - At the conclusion of debate on the Perry amendment No. 26, the Chair put the question on agreeing to the amendment and by voice vote, announced the ayes had prevailed. Ms. Kaptur demanded a recorded vote, and the Chair postponed further proceedings until a time to be announced.",
      "date": "2025-09-03T21:43:59+00:00",
      "organization_id": "~{\"classification\": \"lower\"}",
      "classification": [],
      "related_entities": []
    },
    {
      "description": "DEBATE - Pursuant to the provisions of H. Res. 672, the Committee of the Whole proceeded with 10 minutes of debate on the Perry amendment No. 26.",
      "date": "2025-09-03T21:34:01+00:00",
      "organization_id": "~{\"classification\": \"lower\"}",
      "classification": [],
      "related_entities": []
    },
    {
      "description": "POSTPONED PROCEEDINGS - At the conclusion of debate on the Perry amendment No. 25, the Chair put the question on agreeing to the amendment and by voice vote, announced the ayes had prevailed. Mr. Fleischmann demanded a recorded vote and the Chair postponed further proceedings until a time to be announced.",
      "date": "2025-09-03T21:33:25+00:00",
      "organization_id": "~{\"classification\": \"lower\"}",
      "classification": [],
      "related_entities": []
    },
    {
      "description": "DEBATE - Pursuant to the provisions of H. Res. 672, the Committee of the Whole proceeded with 10 minutes of debate on the Perry amendment No. 25.",
      "date": "2025-09-03T21:29:00+00:00",
      "organization_id": "~{\"classification\": \"lower\"}",
      "classification": [],
      "related_entities": []
    },
    {
      "description": "POSTPONED PROCEEDINGS - At the conclusion of debate on the Perry amendment No. 24, the Chair put the question on agreeing to the amendment and by voice vote, announced the ayes had prevailed. Mr. Fitzpatrick demanded a recorded vote and the Chair postponed further proceedings until a time to be announced.",
      "date": "2025-09-03T21:28:06+00:00",
      "organization_id": "~{\"classification\": \"lower\"}",
      "classification": [],
      "related_entities": []
    },
    {
      "description": "DEBATE - Pursuant to the provisions of H. Res. 672, the Committee of the Whole proceeded with 10 minutes of debate on the Perry amendment No. 24.",
      "date": "2025-09-03T21:22:44+00:00",
      "organization_id": "~{\"classification\": \"lower\"}",
      "classification": [],
      "related_entities": []
    },
    {
      "description": "POSTPONED PROCEEDINGS - At the conclusion of debate on the Perry amendment No. 23, the Chair put the question on agreeing to the amendment and by voice vote, announced the ayes had prevailed. Mr. Fitzpatrick demanded a recorded vote and the Chair postponed further proceedings until a time to be announced.",
      "date": "2025-09-03T21:21:09+00:00",
      "organization_id": "~{\"classification\": \"lower\"}",
      "classification": [],
      "related_entities": []
    },
    {
      "description": "DEBATE - Pursuant to the provisions of H.Res. 672, the Committee of the Whole proceeded with 10 minutes of debate on the Perry amendment No. 23.",
      "date": "2025-09-03T21:14:14+00:00",
      "organization_id": "~{\"classification\": \"lower\"}",
      "classification": [],
      "related_entities": []
    },
    {
      "description": "DEBATE - Pursuant to the provisions of H.Res. 672, the Committee of the Whole proceeded with 10 minutes of debate on the McCormick amendment No. 21.",
      "date": "2025-09-03T21:07:30+00:00",
      "organization_id": "~{\"classification\": \"lower\"}",
      "classification": [],
      "related_entities": []
    },
    {
      "description": "DEBATE - Pursuant to the provisions of H.Res. 672, the Committee of the Whole proceeded with 10 minutes of debate on the Griffith amendment No. 8.",
      "date": "2025-09-03T21:02:01+00:00",
      "organization_id": "~{\"classification\": \"lower\"}",
      "classification": [],
      "related_entities": []
    },
    {
      "description": "DEBATE - Pursuant to the provisions of H.Res. 672, the Committee of the Whole proceeded with 20 minutes of debate on the Fleischmann amendment en bloc.",
      "date": "2025-09-03T20:45:03+00:00",
      "organization_id": "~{\"classification\": \"lower\"}",
      "classification": [],
      "related_entities": []
    },
    {
      "description": "GENERAL DEBATE - The Committee of the Whole proceeded with one hour of general debate on H.R. 4553.",
      "date": "2025-09-03T20:16:19+00:00",
      "organization_id": "~{\"classification\": \"lower\"}",
      "classification": [],
      "related_entities": []
    },
    {
      "description": "The Speaker designated the Honorable Randy Fine to act as Chairman of the Committee.",
      "date": "2025-09-03T20:15:32+00:00",
      "organization_id": "~{\"classification\": \"lower\"}",
      "classification": [],
      "related_entities": []
    },
    {
      "description": "House resolved itself into the Committee of the Whole House on the state of the Union pursuant to H. Res. 672 and Rule XVIII.",
      "date": "2025-09-03T20:15:31+00:00",
      "organization_id": "~{\"classification\": \"lower\"}",
      "classification": [],
      "related_entities": []
    },
    {
      "description": "Rule provides for consideration of H.R. 4553, H.J. Res. 104, H.J. Res. 105 and H.J. Res. 106. The resolution provides for consideration of H.R. 4553 under a structured rule, and H.J. Res. 104, H.J. Res. 105, and H.J. Res. 106 under a closed rule. The resolution provides for one hour of general debate and a motion to recommit on each measure. The resolution further provides that H. Res. 668 and H. Res. 605 are adopted, and H. Res. 598 is laid on the table.",
      "date": "2025-09-03T20:14:03+00:00",
      "organization_id": "~{\"classification\": \"lower\"}",
      "classification": [],
      "related_entities": []
    },
    {
      "description": "Considered under the provisions of rule H. Res. 672. (consideration: CR H3796-3818: 1; text: CR H3799-3807: 1)",
      "date": "2025-09-03T20:13:58+00:00",
      "organization_id": "~{\"classification\": \"lower\"}",
      "classification": [],
      "related_entities": []
    },
    {
      "description": "Rules Committee Resolution H. Res. 672 Reported to House. Rule provides for consideration of H.R. 4553, H.J. Res. 104, H.J. Res. 105 and H.J. Res. 106. The resolution provides for consideration of H.R. 4553 under a structured rule, and H.J. Res. 104, H.J. Res. 105, and H.J. Res. 106 under a closed rule. The resolution provides for one hour of general debate and a motion to recommit on each measure. The resolution further provides that H. Res. 668 and H. Res. 605 are adopted, and H. Res. 598 is laid on the table.",
      "date": "2025-09-03T13:57:13+00:00",
      "organization_id": "~{\"classification\": \"lower\"}",
      "classification": [],
      "related_entities": []
    },
    {
      "description": "Placed on the Union Calendar, Calendar No. 173.",
      "date": "2025-07-21T04:00:00+00:00",
      "organization_id": "~{\"classification\": \"lower\"}",
      "classification": [],
      "related_entities": []
    },
    {
      "description": "The House Committee on Appropriations reported an original measure, H. Rept. 119-213, by Mr. Fleischmann.",
      "date": "2025-07-21T04:00:00+00:00",
      "organization_id": "~{\"classification\": \"lower\"}",
      "classification": [],
      "related_entities": []
    }
  ],
  "sponsorships": [
    {
      "name": "Charles J. \"Chuck\" Fleischmann",
      "classification": "primary",
      "entity_type": "person",
      "primary": true,
      "person_id": "~{\"name\": \"Charles J. \\\"Chuck\\\" Fleischmann\"}",
      "organization_id": null
    }
  ],
  "related_bills": [
    {
      "identifier": "HRES 672",
      "legislative_session": "119",
      "relation_type": "companion"
    }
  ],
  "versions": [
    {
      "note": "Reported in House",
      "links": [
        {
          "url": "https://www.govinfo.gov/content/pkg/BILLS-119hr4553rh/xml/BILLS-119hr4553rh.xml",
          "media_type": "text/xml"
        },
        {
          "url": "https://www.govinfo.gov/content/pkg/BILLS-119hr4553rh/pdf/BILLS-119hr4553rh.pdf",
          "media_type": "application/pdf"
        }
      ],
      "date": "2025-07-21",
      "classification": ""
    }
  ],
  "documents": [
    {
      "note": "HAMDT 73",
      "links": [
        {
          "url": "https://www.congress.gov/amendment/119th-congress/house-amendment/73",
          "media_type": "text/html"
        }
      ],
      "date": "",
      "classification": ""
    },
    {
      "note": "HAMDT 72",
      "links": [
        {
          "url": "https://www.congress.gov/amendment/119th-congress/house-amendment/72",
          "media_type": "text/html"
        }
      ],
      "date": "",
      "classification": ""
    },
    {
      "note": "HAMDT 71",
      "links": [
        {
          "url": "https://www.congress.gov/amendment/119th-congress/house-amendment/71",
          "media_type": "text/html"
        }
      ],
      "date": "",
      "classification": ""
    },
    {
      "note": "HAMDT 70",
      "links": [
        {
          "url": "https://www.congress.gov/amendment/119th-congress/house-amendment/70",
          "media_type": "text/html"
        }
      ],
      "date": "",
      "classification": ""
    },
    {
      "note": "HAMDT 69",
      "links": [
        {
          "url": "https://www.congress.gov/amendment/119th-congress/house-amendment/69",
          "media_type": "text/html"
        }
      ],
      "date": "",
      "classification": ""
    },
    {
      "note": "HAMDT 68",
      "links": [
        {
          "url": "https://www.congress.gov/amendment/119th-congress/house-amendment/68",
          "media_type": "text/html"
        }
      ],
      "date": "",
      "classification": ""
    },
    {
      "note": "HAMDT 67",
      "links": [
        {
          "url": "https://www.congress.gov/amendment/119th-congress/house-amendment/67",
          "media_type": "text/html"
        }
      ],
      "date": "",
      "classification": ""
    },
    {
      "note": "HAMDT 66",
      "links": [
        {
          "url": "https://www.congress.gov/amendment/119th-congress/house-amendment/66",
          "media_type": "text/html"
        }
      ],
      "date": "",
      "classification": ""
    },
    {
      "note": "HAMDT 65",
      "links": [
        {
          "url": "https://www.congress.gov/amendment/119th-congress/house-amendment/65",
          "media_type": "text/html"
        }
      ],
      "date": "",
      "classification": ""
    },
    {
      "note": "HAMDT 64",
      "links": [
        {
          "url": "https://www.congress.gov/amendment/119th-congress/house-amendment/64",
          "media_type": "text/html"
        }
      ],
      "date": "",
      "classification": ""
    },
    {
      "note": "HAMDT 63",
      "links": [
        {
          "url": "https://www.congress.gov/amendment/119th-congress/house-amendment/63",
          "media_type": "text/html"
        }
      ],
      "date": "",
      "classification": ""
    },
    {
      "note": "H. Rept. 119-213",
      "links": [
        {
          "url": "https://www.congress.gov/119/crpt/hrpt213/CRPT-119hrpt213.pdf",
          "media_type": "application/pdf"
        }
      ],
      "date": "",
      "classification": ""
    }
  ],
  "citations": [],
  "sources": [
    {
      "url": "https://www.govinfo.gov/bulkdata/BILLSTATUS/119/hr/BILLSTATUS-119hr4553.xml",
      "note": ""
    },
    {
      "url": "https://congress.gov/bill/119th-congress/house-bill/4553",
      "note": ""
    }
  ],
  "extras": {
    "cosponsor_bioguides": [],
    "sponsor_bioguides": [
      "F000459"
    ]
  },
  "jurisdiction": {
    "id": "ocd-jurisdiction/country:us/government",
    "name": "United States",
    "classification": "country",
    "division_id": "ocd-division/country:us"
  }
}